{
  "latency_aggregate": {
    "max": 3649.536,
    "stdev": 787.88107932174,
    "min": 1249.28,
    "mean": 2453.7734736842
  },
  "duration_in_milliseconds": 5122.615,
  "requests": 79,
  "bytes_transfer_per_second": 4852.9901232086,
  "latency_distribution": [
    {
      "percentile": 50,
      "latency_in_milliseconds": 2478.079
    },
    {
      "percentile": 75,
      "latency_in_milliseconds": 3080.191
    },
    {
      "percentile": 90,
      "latency_in_milliseconds": 3500.031
    },
    {
      "percentile": 95,
      "latency_in_milliseconds": 3620.863
    },
    {
      "percentile": 97.5,
      "latency_in_milliseconds": 3629.055
    },
    {
      "percentile": 99,
      "latency_in_milliseconds": 3649.535
    },
    {
      "percentile": 99.9,
      "latency_in_milliseconds": 3651.583
    },
    {
      "percentile": 99.99,
      "latency_in_milliseconds": 3651.583
    },
    {
      "percentile": 99.999,
      "latency_in_milliseconds": 3651.583
    },
    {
      "percentile": 100,
      "latency_in_milliseconds": 3651.583
    }
  ],
  "bytes": 24860,
  "requests_per_second": 15.42181093055
}
